{
    "metadata": {
        "last_updated": "2024-01-26T10:00:00Z",
        "version": "1.0"
    },
    "priority_levels": {
        "1": {
            "name": "P1",
            "color": "#FF0000"
        },
        "2": {
            "name": "P2",
            "color": "#FF6B00"
        },
        "3": {
            "name": "P3",
            "color": "#FFA500"
        },
        "4": {
            "name": "P4",
            "color": "#FFCC00"
        },
        "5": {
            "name": "P5",
            "color": "#92D050"
        },
        "6": {
            "name": "P6",
            "color": "#00B050"
        }
    },
    "case_priorities": {
        "10736893752": "1",
        "10735016792": "4"
    }
}
